LICENSE
MANIFEST.in
README.md
setup.py
hybrid_methods/__init__.py
hybrid_methods/coherence/__init__.py
hybrid_methods/coherence/hybrid_screen.py
hybrid_methods/fresnel_zone_plate/__init__.py
hybrid_methods/fresnel_zone_plate/hybrid_fresnel_zone_plate.py
hybrid_methods/fresnel_zone_plate/simulator/__init__.py
hybrid_methods/fresnel_zone_plate/simulator/fresnel_zone_plate_simulator.py
hybrid_methods/fresnel_zone_plate/simulator/hankel_transform.py
hybrid_methods/fresnel_zone_plate/simulator/refractive_index.py
hybrid_methods/undulator/__init__.py
shadow_hybrid_methods.egg-info/PKG-INFO
shadow_hybrid_methods.egg-info/SOURCES.txt
shadow_hybrid_methods.egg-info/dependency_links.txt
shadow_hybrid_methods.egg-info/requires.txt
shadow_hybrid_methods.egg-info/top_level.txt
shadow_hybrid_methods.egg-info/zip-safe