Metadata-Version: 2.4
Name: shadow-hybrid-methods
Version: 1.0.15
Summary: Hybrid Methods, combining raytracing with wave optics
Home-page: https://github.com/oasys-kit/hybrid-methods
Download-URL: https://github.com/oasys-kit/hybrid-methods
Author: Luca Rebuffi, Xianbo Shi
Author-email: lrebuffi@anl.gov
Maintainer: Luca Rebuffi
Maintainer-email: lrebuffi@anl.gov
License: BSD
Keywords: x-raysynchrotron radiation,wavefront propagationray tracing,surface metrology,simulation
Classifier: Development Status :: 5 - Production/Stable
Classifier: Environment :: Console
Classifier: Environment :: Plugins
Classifier: Programming Language :: Python :: 3
Classifier: License :: OSI Approved :: GNU General Public License v3 or later (GPLv3+)
Classifier: Operating System :: POSIX
Classifier: Operating System :: Microsoft :: Windows
Classifier: Topic :: Scientific/Engineering :: Visualization
Classifier: Topic :: Software Development :: Libraries :: Python Modules
Classifier: Intended Audience :: Education
Classifier: Intended Audience :: Science/Research
Classifier: Intended Audience :: Developers
License-File: LICENSE
Requires-Dist: setuptools
Requires-Dist: numpy
Requires-Dist: scipy
Requires-Dist: srxraylib>=1.0.45
Requires-Dist: syned
Requires-Dist: wofry
Requires-Dist: wofryimpl>=1.0.26
Dynamic: author
Dynamic: author-email
Dynamic: classifier
Dynamic: description
Dynamic: download-url
Dynamic: home-page
Dynamic: keywords
Dynamic: license
Dynamic: license-file
Dynamic: maintainer
Dynamic: maintainer-email
Dynamic: requires-dist
Dynamic: summary
